console/__init__.py
console/compose_client.py
console/http_server.py
ml_pipe_core/__init__.py
ml_pipe_core/agent_result_message.py
ml_pipe_core/command.py
ml_pipe_core/config.py
ml_pipe_core/logger.py
ml_pipe_core/machine_topics.py
ml_pipe_core/message.py
ml_pipe_core/service.py
ml_pipe_core/simple_service.py
ml_pipe_core/simple_service_message.py
ml_pipe_core/topics.py
ml_pipe_core/adapter/MsgBusWriter.py
ml_pipe_core/adapter/__init__.py
ml_pipe_core/client/__init__.py
ml_pipe_core/client/kafka_client.py
ml_pipe_core/client/service_client.py
ml_pipe_core/client/utils.py
ml_pipe_core/event_utls/__init__.py
ml_pipe_core/event_utls/consumer.py
ml_pipe_core/event_utls/consumer_thread.py
ml_pipe_core/event_utls/producer.py
ml_pipe_core/simulation/MachineService.py
ml_pipe_core/simulation/SimulationService.py
ml_pipe_core/simulation/TimedSimService.py
ml_pipe_core/simulation/__init__.py
ml_pipe_core/simulation/update_message_types.py
ml_pipe_core/simulation/utils.py
ml_pipe_core/simulation/physics_based/__init__.py
ml_pipe_core/simulation/physics_based/p3_elements_v24.py
ml_pipe_core/simulation/physics_based/p3_elements_v24_c4l.py
ml_pipe_core/utils/SqlDBConnector.py
ml_pipe_core/utils/TimerThread.py
ml_pipe_core/utils/__init__.py
ml_pipe_core/utils/sql_utils.py
ml_pipe_core/utils/utils.py
ml_pipe_core-0.0.23.dist-info/LICENSE
ml_pipe_core-0.0.23.dist-info/METADATA
ml_pipe_core-0.0.23.dist-info/WHEEL
ml_pipe_core-0.0.23.dist-info/top_level.txt
ml_pipe_core-0.0.23.dist-info/RECORD
